deepsynth/__init__.py
deepsynth/hyperparameter_optimization.py
deepsynth/model_generation.py
deepsynth/nas.py
deepsynth/transfer_learning.py
deepsynth/visualization.py
deepsynth-0.1.3.dist-info/LICENSE
deepsynth-0.1.3.dist-info/METADATA
deepsynth-0.1.3.dist-info/WHEEL
deepsynth-0.1.3.dist-info/entry_points.txt
deepsynth-0.1.3.dist-info/RECORD
