Metadata-Version: 2.1
Name: deepsynth
Version: 0.1.3
Summary: A Python package for synthesizing deep learning models using advanced techniques like NAS, Hyperparameter Optimization, and more.
Home-page: https://github.com/venombolteop/deepsynth
License: MIT
Author: venombolteop
Author-email: venombolteop@gmail.com
Requires-Python: >=3.10,<4.0
Classifier: License :: OSI Approved :: MIT License
Classifier: Programming Language :: Python :: 3
Classifier: Programming Language :: Python :: 3.10
Classifier: Programming Language :: Python :: 3.11
Classifier: Programming Language :: Python :: 3.12
Requires-Dist: h5py (>=3.9.0,<4.0.0)
Requires-Dist: hyperopt
Requires-Dist: keras
Requires-Dist: numpy (>=1.23.5,<2.0.0)
Requires-Dist: tensorflow (==2.17.0)
Project-URL: Documentation, https://github.com/venombolteop/deepsynth/wiki
Project-URL: Repository, https://github.com/venombolteop/deepsynth
